comp_match-0.0.0.dev0.dist-info/DESCRIPTION.rst
comp_match-0.0.0.dev0.dist-info/METADATA
comp_match-0.0.0.dev0.dist-info/RECORD
comp_match-0.0.0.dev0.dist-info/WHEEL
comp_match-0.0.0.dev0.dist-info/metadata.json
comp_match-0.0.0.dev0.dist-info/top_level.txt
matchers/__init__.py
matchers/_utils.py
matchers/base.py
matchers/google_finance.py
matchers/yahoo_finance.py
matchers/resources/exchanges.json
matchers/resources/iso_countries.json
